api.py
app.py
streamlit_business_inteligence.py
utils.py
pages/call_api.py
pages/delete_query.py
pages/delete_table.py
pages/plot_results.py
pages/save_query.py
pages/upload_data.py
streamlit_business_intelligence-0.0.3.dist-info/METADATA
streamlit_business_intelligence-0.0.3.dist-info/WHEEL
streamlit_business_intelligence-0.0.3.dist-info/entry_points.txt
streamlit_business_intelligence-0.0.3.dist-info/top_level.txt
streamlit_business_intelligence-0.0.3.dist-info/RECORD
