Metadata-Version: 2.1
Name: streamlit-business-intelligence
Version: 0.0.3
Summary: Python library for SQL Data Analysis
Home-page: https://github.com/GeorgePearse/streamlit-projects/tree/master/streamlit-bi
Author: George Pearse
Author-email: georgehwp26@gmail.com
License: MIT
Classifier: Development Status :: 3 - Alpha
Classifier: Intended Audience :: Developers
Classifier: Topic :: Software Development
Classifier: License :: OSI Approved :: MIT License
Classifier: Operating System :: OS Independent
Classifier: Programming Language :: Python :: 3.6
Requires-Dist: streamlit
Requires-Dist: pandas
Requires-Dist: plotly
